{
   "format" : "schoolNRa factor denoting the school.\n\npupilNRa factor denoting the pupil.\n\nIQ.verba numeric vector of verbal IQ scores\n\nIQ.perfa numeric vector of IQ scores.\n\nsexSex of the student.\n\nMinoritya factor indicating if the student is a member of a\nminority group.\n\nrepeatgran ordered factor indicating if one or more grades\nhave been repeated.\n\naritPRETa numeric vector\n\nclassNRa numeric vector\n\naritPOSTa numeric vector\n\nlangPRETa numeric vector\n\nlangPOSTa numeric vector\n\nsesa numeric vector of socioeconomic status indicators.\n\ndenominaa factor indicating of the school is a public\nschool, a Protestant private school, a Catholic private school, or\na non-denominational private school.\n\nschoolSESa numeric vector\n\nsatiprina numeric vector\n\nnatitesta factor with levels 0 and 1\n\nmeetingsa numeric vector\n\ncurrmeeta numeric vector\n\nmixedgraa factor indicating if the class is a mixed-grade class.\n\npercminoa numeric vector\n\naritdiffa numeric vector\n\nhomeworka numeric vector\n\nclasssiza numeric vector\n\ngroupsiza numeric vector",
   "parameters" : {
      "mixedgra" : "a factor indicating if the class is a mixed-grade class.",
      "denomina" : "a factor indicating of the school is a public\nschool, a Protestant private school, a Catholic private school, or\na non-denominational private school.",
      "meetings" : "a numeric vector",
      "IQ.perf" : "a numeric vector of IQ scores.",
      "homework" : "a numeric vector",
      "schoolSES" : "a numeric vector",
      "satiprin" : "a numeric vector",
      "repeatgr" : "an ordered factor indicating if one or more grades\nhave been repeated.",
      "aritdiff" : "a numeric vector",
      "Minority" : "a factor indicating if the student is a member of a\nminority group.",
      "IQ.verb" : "a numeric vector of verbal IQ scores",
      "sex" : "Sex of the student.",
      "aritPOST" : "a numeric vector",
      "percmino" : "a numeric vector",
      "langPRET" : "a numeric vector",
      "natitest" : "a factor with levels 0 and 1",
      "aritPRET" : "a numeric vector",
      "langPOST" : "a numeric vector",
      "classsiz" : "a numeric vector",
      "ses" : "a numeric vector of socioeconomic status indicators.",
      "classNR" : "a numeric vector",
      "schoolNR" : "a factor denoting the school.",
      "groupsiz" : "a numeric vector",
      "currmeet" : "a numeric vector",
      "pupilNR" : "a factor denoting the pupil."
   },
   "reference" : "&lsquo;&#8288;http://stat.gamma.rug.nl/snijders/multilevel.htm&#8288;&rsquo;, the first\nedition of http://www.stats.ox.ac.uk/~snijders/mlbook.htm.",
   "usage" : "data(bdf)",
   "title" : "Language scores",
   "description" : "Description\nThe bdf data frame has 2287 rows and 25 columns of language\nscores from grade 8 pupils in elementary schools in The Netherlands."
}
